MakeSingular/PluralToSingular.py
MakeSingular/__init__.py
MakeSingular/stopwords.txt
MakeSingular-0.0.1.dist-info/LICENSE
MakeSingular-0.0.1.dist-info/METADATA
MakeSingular-0.0.1.dist-info/WHEEL
MakeSingular-0.0.1.dist-info/top_level.txt
MakeSingular-0.0.1.dist-info/RECORD
